pyhw/__init__.py
pyhw/__main__.py
pyhw/backend/__init__.py
pyhw/backend/backendBase.py
pyhw/backend/cpu/__init__.py
pyhw/backend/cpu/bsd.py
pyhw/backend/cpu/cpuBase.py
pyhw/backend/cpu/cpuInfo.py
pyhw/backend/cpu/linux.py
pyhw/backend/cpu/macos.py
pyhw/backend/cpu/windows.py
pyhw/backend/gpu/__init__.py
pyhw/backend/gpu/bsd.py
pyhw/backend/gpu/gpuBase.py
pyhw/backend/gpu/gpuInfo.py
pyhw/backend/gpu/linux.py
pyhw/backend/gpu/macos.py
pyhw/backend/gpu/windows.py
pyhw/backend/host/__init__.py
pyhw/backend/host/bsd.py
pyhw/backend/host/hostBase.py
pyhw/backend/host/hostInfo.py
pyhw/backend/host/linux.py
pyhw/backend/host/macos.py
pyhw/backend/host/windows.py
pyhw/backend/kernel/__init__.py
pyhw/backend/kernel/kernelBase.py
pyhw/backend/kernel/kernelInfo.py
pyhw/backend/kernel/unix.py
pyhw/backend/kernel/windows.py
pyhw/backend/memory/__init__.py
pyhw/backend/memory/bsd.py
pyhw/backend/memory/linux.py
pyhw/backend/memory/macos.py
pyhw/backend/memory/memoryBase.py
pyhw/backend/memory/memoryInfo.py
pyhw/backend/memory/windows.py
pyhw/backend/nic/__init__.py
pyhw/backend/nic/bsd.py
pyhw/backend/nic/linux.py
pyhw/backend/nic/macos.py
pyhw/backend/nic/nicBase.py
pyhw/backend/nic/nicInfo.py
pyhw/backend/nic/windows.py
pyhw/backend/npu/__init__.py
pyhw/backend/npu/bsd.py
pyhw/backend/npu/linux.py
pyhw/backend/npu/macos.py
pyhw/backend/npu/npuBase.py
pyhw/backend/npu/npuInfo.py
pyhw/backend/npu/windows.py
pyhw/backend/os/__init__.py
pyhw/backend/os/bsd.py
pyhw/backend/os/linux.py
pyhw/backend/os/macos.py
pyhw/backend/os/osBase.py
pyhw/backend/os/osInfo.py
pyhw/backend/os/windows.py
pyhw/backend/shell/__init__.py
pyhw/backend/shell/shellBase.py
pyhw/backend/shell/shellInfo.py
pyhw/backend/shell/unix.py
pyhw/backend/shell/windows.py
pyhw/backend/title/__init__.py
pyhw/backend/title/titleBase.py
pyhw/backend/title/titleInfo.py
pyhw/backend/title/unix.py
pyhw/backend/title/windows.py
pyhw/backend/uptime/__init__.py
pyhw/backend/uptime/bsd.py
pyhw/backend/uptime/linux.py
pyhw-0.16.3.dist-info/licenses/LICENSE
pyhw-0.16.3.dist-info/METADATA
pyhw-0.16.3.dist-info/WHEEL
pyhw-0.16.3.dist-info/entry_points.txt
pyhw-0.16.3.dist-info/top_level.txt
pyhw-0.16.3.dist-info/RECORD
