Metadata-Version: 2.4
Name: pyhw
Version: 0.16.3
Summary: PyHw, a neofetch-like command line tool for fetching system information but written mostly in python.
Author: Xiao Ran
Maintainer-email: Xiao Ran <xiaoran.007@icloud.com>
License-Expression: BSD-3-Clause
Project-URL: homepage, https://github.com/xiaoran007/pyhw
Keywords: neofetch,system information,command line tool,python,hardware information,fastfetch,fetching
Classifier: Development Status :: 5 - Production/Stable
Classifier: Programming Language :: Python :: 3
Classifier: Operating System :: OS Independent
Requires-Python: >=3.9
License-File: LICENSE
Requires-Dist: pypci-ng>=0.3.3
Dynamic: license-file
